DESCRIPTION
HISTORY.rst
MANIFEST.in
README.rst
VERSION
conftest.py
findpackages.py
requirements.txt
setup.py
Flask_LwAdmin.egg-info/PKG-INFO
Flask_LwAdmin.egg-info/SOURCES.txt
Flask_LwAdmin.egg-info/dependency_links.txt
Flask_LwAdmin.egg-info/not-zip-safe
Flask_LwAdmin.egg-info/requires.txt
Flask_LwAdmin.egg-info/top_level.txt
SAMPLE_PROJECT/__init__.py
SAMPLE_PROJECT/myapp.py
SAMPLE_PROJECT/myapp2.py
SAMPLE_PROJECT/myapp3.py
docs/development.rst
flask_lwadmin/__init__.py
flask_lwadmin/config.py
flask_lwadmin/form.py
flask_lwadmin/navbar.py
flask_lwadmin/pager.py
flask_lwadmin/static/favicon.ico
flask_lwadmin/static/css/jquery-ui-timepicker-addon.css
flask_lwadmin/static/css/lw-admin.css
flask_lwadmin/static/css/smoothness/jquery-ui-1.10.1.custom.css
flask_lwadmin/static/css/smoothness/jquery-ui-1.10.1.custom.min.css
flask_lwadmin/static/css/smoothness/images/animated-overlay.gif
flask_lwadmin/static/css/smoothness/images/ui-bg_flat_0_aaaaaa_40x100.png
flask_lwadmin/static/css/smoothness/images/ui-bg_flat_75_ffffff_40x100.png
flask_lwadmin/static/css/smoothness/images/ui-bg_glass_55_fbf9ee_1x400.png
flask_lwadmin/static/css/smoothness/images/ui-bg_glass_65_ffffff_1x400.png
flask_lwadmin/static/css/smoothness/images/ui-bg_glass_75_dadada_1x400.png
flask_lwadmin/static/css/smoothness/images/ui-bg_glass_75_e6e6e6_1x400.png
flask_lwadmin/static/css/smoothness/images/ui-bg_glass_95_fef1ec_1x400.png
flask_lwadmin/static/css/smoothness/images/ui-bg_highlight-soft_75_cccccc_1x100.png
flask_lwadmin/static/css/smoothness/images/ui-icons_222222_256x240.png
flask_lwadmin/static/css/smoothness/images/ui-icons_2e83ff_256x240.png
flask_lwadmin/static/css/smoothness/images/ui-icons_454545_256x240.png
flask_lwadmin/static/css/smoothness/images/ui-icons_888888_256x240.png
flask_lwadmin/static/css/smoothness/images/ui-icons_cd0a0a_256x240.png
flask_lwadmin/static/img/error.png
flask_lwadmin/static/img/footer-gradient.png
flask_lwadmin/static/img/logo.png
flask_lwadmin/static/img/menu-main-gradient.png
flask_lwadmin/static/img/menu-sub-gradient-empty.png
flask_lwadmin/static/img/menu-sub-gradient.png
flask_lwadmin/static/img/priority_down.png
flask_lwadmin/static/img/priority_first.png
